[
  {
    "ronde": "ronde 1",
    "datum": "07-02-2020",
    "partijen": [
      {
        "wr": "",
        "zr": "",
        "wit": "Bye 1",
        "zwart": "Bye 2"
      },
      {
        "wr": "0",
        "zr": "1",
        "wit": "Niels Lerinckx",
        "zwart": "Sander Lerinckx"
      },
      {
        "wr": "",
        "zr": "",
        "wit": "Matthias Vanrossum",
        "zwart": "Felix Huyghe"
      },
      {
        "wr": "",
        "zr": "",
        "wit": "Mats Laureys",
        "zwart": "Jannes Vandevelde"
      }
    ]
  },
  {
    "ronde": "ronde 2",
    "datum": "21-02-2020",
    "partijen": [
      {
        "wr": "",
        "zr": "",
        "wit": "Bye 2",
        "zwart": "Jannes Vandevelde"
      },
      {
        "wr": "",
        "zr": "",
        "wit": "Felix Huyghe",
        "zwart": "Mats Laureys"
      },
      {
        "wr": "",
        "zr": "",
        "wit": "Sander Lerinckx",
        "zwart": "Matthias Vanrossum"
      },
      {
        "wr": "",
        "zr": "",
        "wit": "Bye 1",
        "zwart": "Niels Lerinckx"
      }
    ]
  },
  {
    "ronde": "ronde 3",
    "datum": "06-03-2020",
    "partijen": [
      {
        "wr": "",
        "zr": "",
        "wit": "Niels Lerinckx",
        "zwart": "Bye 2"
      },
      {
        "wr": "",
        "zr": "",
        "wit": "Matthias Vanrossum",
        "zwart": "Bye 1"
      },
      {
        "wr": "",
        "zr": "",
        "wit": "Mats Laureys",
        "zwart": "Sander Lerinckx"
      },
      {
        "wr": "",
        "zr": "",
        "wit": "Jannes Vandevelde",
        "zwart": "Felix Huyghe"
      }
    ]
  },
  {
    "ronde": "ronde 4",
    "datum": "20-03-2020",
    "partijen": [
      {
        "wr": "",
        "zr": "",
        "wit": "Bye 2",
        "zwart": "Felix Huyghe"
      },
      {
        "wr": "",
        "zr": "",
        "wit": "Sander Lerinckx",
        "zwart": "Jannes Vandevelde"
      },
      {
        "wr": "",
        "zr": "",
        "wit": "Bye 1",
        "zwart": "Mats Laureys"
      },
      {
        "wr": "",
        "zr": "",
        "wit": "Niels Lerinckx",
        "zwart": "Matthias Vanrossum"
      }
    ]
  },
  {
    "ronde": "ronde 5",
    "datum": "03-04-2020",
    "partijen": [
      {
        "wr": "",
        "zr": "",
        "wit": "Matthias Vanrossum",
        "zwart": "Bye 2"
      },
      {
        "wr": "",
        "zr": "",
        "wit": "Mats Laureys",
        "zwart": "Niels Lerinckx"
      },
      {
        "wr": "",
        "zr": "",
        "wit": "Jannes Vandevelde",
        "zwart": "Bye 1"
      },
      {
        "wr": "",
        "zr": "",
        "wit": "Felix Huyghe",
        "zwart": "Sander Lerinckx"
      }
    ]
  },
  {
    "ronde": "ronde 6",
    "datum": "01-05-2020",
    "partijen": [
      {
        "wr": "",
        "zr": "",
        "wit": "Bye 2",
        "zwart": "Sander Lerinckx"
      },
      {
        "wr": "",
        "zr": "",
        "wit": "Bye 1",
        "zwart": "Felix Huyghe"
      },
      {
        "wr": "",
        "zr": "",
        "wit": "Niels Lerinckx",
        "zwart": "Jannes Vandevelde"
      },
      {
        "wr": "",
        "zr": "",
        "wit": "Matthias Vanrossum",
        "zwart": "Mats Laureys"
      }
    ]
  },
  {
    "ronde": "ronde 7",
    "datum": "22-05-2020",
    "partijen": [
      {
        "wr": "",
        "zr": "",
        "wit": "Mats Laureys",
        "zwart": "Bye 2"
      },
      {
        "wr": "",
        "zr": "",
        "wit": "Jannes Vandevelde",
        "zwart": "Matthias Vanrossum"
      },
      {
        "wr": "",
        "zr": "",
        "wit": "Felix Huyghe",
        "zwart": "Niels Lerinckx"
      },
      {
        "wr": "",
        "zr": "",
        "wit": "Sander Lerinckx",
        "zwart": "Bye 1"
      }
    ]
  }
]