[
  {
    "ronde": "1",
    "datum": "03-10-1999",
    "thuis": "228 Dworp 2",
    "uit": "203 Fous du Roy 2",
    "tscore": "2",
    "uscore": "2",
    "tgem": "1802",
    "ugem": "1642",
    "borden": [
      {"tr": "0.5", "ur": "0.5", "tspeler": "Pletinckx Eddy", "uspeler": "Karagoulian Gary", "telo": "1845", "uelo": "1743", "tstam": "76325", "ustam": "82848"},
      {"tr": "1", "ur": "0", "tspeler": "Maeckelbergh Mieke", "uspeler": "Sonnaert Pierre", "telo": "1842", "uelo": "1672", "tstam": "353", "ustam": "76937"},
      {"tr": "0.5", "ur": "0.5", "tspeler": "Lemmens Pierre", "uspeler": "Gervais Jacques", "telo": "1774", "uelo": "1607", "tstam": "43419", "ustam": "2941"},
      {"tr": "0", "ur": "1", "tspeler": "van Duuren Louis", "uspeler": "Mouradian Azat", "telo": "1748", "uelo": "1546", "tstam": "26816", "ustam": "79201"}
    ]
  },
  {
    "ronde": "2",
    "datum": "17-10-1999",
    "thuis": "204 Excelsior 1",
    "uit": "228 Dworp 2",
    "tscore": "1.5",
    "uscore": "2.5",
    "tgem": "1746",
    "ugem": "1800",
    "borden": [
      {"tr": "1", "ur": "0", "tspeler": "Atanasiu Nicolae", "uspeler": "Lot Diederik", "telo": "1946", "uelo": "1831", "tstam": "24856", "ustam": "9954"},
      {"tr": "0", "ur": "1", "tspeler": "Verschoren Fran\u00e7ois", "uspeler": "Pletinckx Eddy", "telo": "1721", "uelo": "1845", "tstam": "41688", "ustam": "76325"},
      {"tr": "0", "ur": "1", "tspeler": "Pagnoul Alex", "uspeler": "Lemmens Pierre", "telo": "1769", "uelo": "1774", "tstam": "9334", "ustam": "43419"},
      {"tr": "0.5", "ur": "0.5", "tspeler": "Petr\u00e9 Rudy", "uspeler": "van Duuren Louis", "telo": "1547", "uelo": "1748", "tstam": "12068", "ustam": "26816"}
    ]
  },
  {
    "ronde": "3",
    "datum": "31-10-1999",
    "thuis": "228 Dworp 2",
    "uit": "607 Rochade Eupen 4",
    "tscore": "3",
    "uscore": "1",
    "tgem": "1833",
    "ugem": "1819",
    "borden": [
      {"tr": "0.5", "ur": "0.5", "tspeler": "Lot Diederik", "uspeler": "Simons Jean", "telo": "1831", "uelo": "1896", "tstam": "9954", "ustam": "48895"},
      {"tr": "1", "ur": "0", "tspeler": "Malfliet Bernard", "uspeler": "Zagozen Franz", "telo": "1881", "uelo": "1880", "tstam": "31348", "ustam": "99554"},
      {"tr": "1", "ur": "0", "tspeler": "Pletinckx Eddy", "uspeler": "Godesar Guenter", "telo": "1845", "uelo": "1753", "tstam": "76325", "ustam": "99805"},
      {"tr": "0.5", "ur": "0.5", "tspeler": "Lemmens Pierre", "uspeler": "Charlier Norbert", "telo": "1774", "uelo": "1747", "tstam": "43419", "ustam": "15709"}
    ]
  },
  {
    "ronde": "4",
    "datum": "14-11-1999",
    "thuis": "239 Boitsfort 2",
    "uit": "228 Dworp 2",
    "tscore": "2.5",
    "uscore": "1.5",
    "tgem": "1928",
    "ugem": "1800",
    "borden": [
      {"tr": "1", "ur": "0", "tspeler": "Dohogne Yves", "uspeler": "Lot Diederik", "telo": "2041", "uelo": "1831", "tstam": "66184", "ustam": "9954"},
      {"tr": "1", "ur": "0", "tspeler": "Peeters Yves", "uspeler": "Pletinckx Eddy", "telo": "1951", "uelo": "1845", "tstam": "81922", "ustam": "76325"},
      {"tr": "0.5", "ur": "0.5", "tspeler": "Silovy Alain", "uspeler": "Lemmens Pierre", "telo": "1861", "uelo": "1774", "tstam": "87823", "ustam": "43419"},
      {"tr": "0", "ur": "1", "tspeler": "Lacrosse Bernard", "uspeler": "van Duuren Louis", "telo": "1858", "uelo": "1748", "tstam": "36633", "ustam": "26816"}
    ]
  },
  {
    "ronde": "5",
    "datum": "28-11-1999",
    "thuis": "263 Aarschot 1",
    "uit": "228 Dworp 2",
    "tscore": "2",
    "uscore": "2",
    "tgem": "1778",
    "ugem": "1745",
    "borden": [
      {"tr": "0.5", "ur": "0.5", "tspeler": "Vets Nelis", "uspeler": "Pletinckx Eddy", "telo": "1847", "uelo": "1845", "tstam": "13731", "ustam": "76325"},
      {"tr": "1", "ur": "0", "tspeler": "Verduyct Johan", "uspeler": "Lemmens Pierre", "telo": "1844", "uelo": "1774", "tstam": "46361", "ustam": "43419"},
      {"tr": "0", "ur": "1", "tspeler": "Janssens Ewald", "uspeler": "van Duuren Louis", "telo": "1768", "uelo": "1748", "tstam": "21636", "ustam": "26816"},
      {"tr": "0.5", "ur": "0.5", "tspeler": "Dauw Tonny", "uspeler": "Van der Voorde Sonja", "telo": "1653", "uelo": "1611", "tstam": "48691", "ustam": "43346"}
    ]
  },
  {
    "ronde": "6",
    "datum": "12-12-1999",
    "thuis": "228 Dworp 2",
    "uit": "166 TSM Mechelen 3",
    "tscore": "4",
    "uscore": "0",
    "tgem": "1761",
    "ugem": "1869",
    "borden": [
      {"tr": "1", "ur": "0", "tspeler": "(forfait)", "uspeler": "(forfait)", "telo": "", "uelo": "", "tstam": "", "ustam": ""},
      {"tr": "1", "ur": "0", "tspeler": "(forfait)", "uspeler": "(forfait)", "telo": "", "uelo": "", "tstam": "", "ustam": ""},
      {"tr": "1", "ur": "0", "tspeler": "Lemmens Pierre", "uspeler": "Verbruggen Jean", "telo": "1774", "uelo": "1869", "tstam": "43419", "ustam": "23281"},
      {"tr": "1", "ur": "0", "tspeler": "van Duuren Louis", "uspeler": "n.m.", "telo": "1748", "uelo": "", "tstam": "26816", "ustam": ""}
    ]
  },
  {
    "ronde": "7",
    "datum": "09-01-2000",
    "thuis": "272 Tib\u00e9checs 1",
    "uit": "228 Dworp 2",
    "tscore": "3.5",
    "uscore": "0.5",
    "tgem": "1835",
    "ugem": "1833",
    "borden": [
      {"tr": "1", "ur": "0", "tspeler": "Couillard Marc", "uspeler": "Lot Diederik", "telo": "1922", "uelo": "1831", "tstam": "42307", "ustam": "9954"},
      {"tr": "1", "ur": "0", "tspeler": "Rauta Nicolas", "uspeler": "Malfliet Bernard", "telo": "1865", "uelo": "1881", "tstam": "68497", "ustam": "31348"},
      {"tr": "1", "ur": "0", "tspeler": "Rodriguez Garcia Cristobal", "uspeler": "Pletinckx Eddy", "telo": "1737", "uelo": "1845", "tstam": "70017", "ustam": "76325"},
      {"tr": "0.5", "ur": "0.5", "tspeler": "Ben Khayat El Hadi", "uspeler": "Lemmens Pierre", "telo": "1816", "uelo": "1774", "tstam": "66354", "ustam": "43419"}
    ]
  },
  {
    "ronde": "8",
    "datum": "23-01-2000",
    "thuis": "228 Dworp 2",
    "uit": "501 CRE Charleroi 3",
    "tscore": "2.5",
    "uscore": "1.5",
    "tgem": "1625",
    "ugem": "1371",
    "borden": [
      {"tr": "0.5", "ur": "0.5", "tspeler": "Lot Diederik", "uspeler": "Soretti Vincenzo", "telo": "1831", "uelo": "1523", "tstam": "9954", "ustam": "78549"},
      {"tr": "0.5", "ur": "0.5", "tspeler": "Malfliet Bernard", "uspeler": "Jadouille Olivier", "telo": "1881", "uelo": "1516", "tstam": "31348", "ustam": "59579"},
      {"tr": "1", "ur": "0", "tspeler": "Malfliet Koen", "uspeler": "Simal Amaury", "telo": "1552", "uelo": "1279", "tstam": "64327", "ustam": "84476"},
      {"tr": "0.5", "ur": "0.5", "tspeler": "Heremans Gersende", "uspeler": "Krasucki Paul", "telo": "1234", "uelo": "1164", "tstam": "2259", "ustam": "79696"}
    ]
  },
  {
    "ronde": "9",
    "datum": "06-02-2000",
    "thuis": "244 Wol-Thib 3",
    "uit": "228 Dworp 2",
    "tscore": "2.5",
    "uscore": "1.5",
    "tgem": "1797",
    "ugem": "1671",
    "borden": [
      {"tr": "0.5", "ur": "0.5", "tspeler": "Kemele Willy", "uspeler": "Pletinckx Eddy", "telo": "1830", "uelo": "1845", "tstam": "17906", "ustam": "76325"},
      {"tr": "0", "ur": "1", "tspeler": "Citti Pierre", "uspeler": "Lemmens Pierre", "telo": "1808", "uelo": "1774", "tstam": "79689", "ustam": "43419"},
      {"tr": "1", "ur": "0", "tspeler": "Lambert Michel", "uspeler": "Van der Voorde Sonja", "telo": "1795", "uelo": "1611", "tstam": "80918", "ustam": "43346"},
      {"tr": "1", "ur": "0", "tspeler": "Van Loo Georges", "uspeler": "Dekoster Pascal", "telo": "1754", "uelo": "1452", "tstam": "52094", "ustam": "54658"}
    ]
  },
  {
    "ronde": "10",
    "datum": "20-02-2000",
    "thuis": "228 Dworp 2",
    "uit": "229 Woluw\u00e9 2",
    "tscore": "2.5",
    "uscore": "1.5",
    "tgem": "1532",
    "ugem": "1377",
    "borden": [
      {"tr": "1", "ur": "0", "tspeler": "(forfait)", "uspeler": "(forfait)", "telo": "", "uelo": "", "tstam": "", "ustam": ""},
      {"tr": "1", "ur": "0", "tspeler": "(forfait)", "uspeler": "(forfait)", "telo": "", "uelo": "", "tstam": "", "ustam": ""},
      {"tr": "0.5", "ur": "0.5", "tspeler": "Van der Voorde Sonja", "uspeler": "Matinfar Mohammed", "telo": "1611", "uelo": "1414", "tstam": "43346", "ustam": "74543"},
      {"tr": "0", "ur": "1", "tspeler": "Dekoster Pascal", "uspeler": "Geerinckx Bernard", "telo": "1452", "uelo": "1340", "tstam": "54658", "ustam": "94901"}
    ]
  },
  {
    "ronde": "11",
    "datum": "19-03-2000",
    "thuis": "209 Anderlecht 4",
    "uit": "228 Dworp 2",
    "tscore": "2",
    "uscore": "2",
    "tgem": "1643",
    "ugem": "1630",
    "borden": [
      {"tr": "1", "ur": "0", "tspeler": "Vanderhelstraete Jean Jacques", "uspeler": "Lot Diederik", "telo": "1694", "uelo": "1831", "tstam": "31739", "ustam": "9954"},
      {"tr": "0", "ur": "1", "tspeler": "Tonoli Benjamin", "uspeler": "Pletinckx Eddy", "telo": "1613", "uelo": "1845", "tstam": "16365", "ustam": "76325"},
      {"tr": "0.5", "ur": "0.5", "tspeler": "Delvaux Jacques", "uspeler": "Van der Voorde Sonja", "telo": "1662", "uelo": "1611", "tstam": "18538", "ustam": "43346"},
      {"tr": "0.5", "ur": "0.5", "tspeler": "Rando Manuel", "uspeler": "Heremans Gersende", "telo": "1602", "uelo": "1234", "tstam": "67164", "ustam": "2259"}
    ]
  }
]