[
  {
    "ronde": "ronde 1",
    "datum": "02-10-2020",
    "partijen": [
      {
        "wr": "",
        "zr": "",
        "wit": "Yves Baert",
        "zwart": "Tom Van Hoofstat"
      },
      {
        "wr": "0.5",
        "zr": "0.5",
        "wit": "Jannes Vandevelde",
        "zwart": "Serge Vanderwaeren"
      },
      {
        "wr": "0.5",
        "zr": "0.5",
        "wit": "Pascal Dekoster",
        "zwart": "Mats Laureys"
      },
      {
        "wr": "0",
        "zr": "1",
        "wit": "Niels Lerinckx",
        "zwart": "Peter De Bosscher"
      },
      {
        "wr": "1",
        "zr": "0",
        "wit": "Eddy Pletinckx",
        "zwart": "Niels Palmans"
      },
      {
        "wr": "0",
        "zr": "1",
        "wit": "Sander Lerinckx",
        "zwart": "Eric Cornelis"
      },
      {
        "wr": "",
        "zr": "",
        "wit": "Geert Verrijken",
        "zwart": "Yentl Wilmots"
      },
      {
        "wr": "0",
        "zr": "1",
        "wit": "Mathias Vanrossum",
        "zwart": "Diederik Lot"
      }
    ]
  },
  {
    "ronde": "ronde 2",
    "datum": "16-10-2020",
    "partijen": [
      {
        "wr": "",
        "zr": "",
        "wit": "Tom Van Hoofstat",
        "zwart": "Diederik Lot"
      },
      {
        "wr": "",
        "zr": "",
        "wit": "Yentl Wilmots",
        "zwart": "Mathias Vanrossum"
      },
      {
        "wr": "",
        "zr": "",
        "wit": "Eric Cornelis",
        "zwart": "Geert Verrijken"
      },
      {
        "wr": "",
        "zr": "",
        "wit": "Niels Palmans",
        "zwart": "Sander Lerinckx"
      },
      {
        "wr": "1",
        "zr": "0",
        "wit": "Peter De Bosscher",
        "zwart": "Eddy Pletinckx"
      },
      {
        "wr": "1",
        "zr": "0",
        "wit": "Mats Laureys",
        "zwart": "Niels Lerinckx"
      },
      {
        "wr": "1",
        "zr": "0",
        "wit": "Serge Vanderwaeren",
        "zwart": "Pascal Dekoster"
      },
      {
        "wr": "1",
        "zr": "0",
        "wit": "Yves Baert",
        "zwart": "Jannes Vandevelde"
      }
    ]
  }
]
